MANIFEST.in
changelog.rst
readme.rst
setup.py
BaseBWA.egg-info/PKG-INFO
BaseBWA.egg-info/SOURCES.txt
BaseBWA.egg-info/dependency_links.txt
BaseBWA.egg-info/entry_points.txt
BaseBWA.egg-info/not-zip-safe
BaseBWA.egg-info/requires.txt
BaseBWA.egg-info/top_level.txt
basebwa/__init__.py
basebwa/application.py
basebwa/application.py~
basebwa/version.txt
basebwa/components/__init__.py
basebwa/components/apputil/__init__.py
basebwa/components/apputil/forms.py
basebwa/components/apputil/forms.py~
basebwa/components/apputil/settings.py
basebwa/components/apputil/settings.py~
basebwa/components/apputil/views.py
basebwa/components/apputil/views.py~
basebwa/components/apputil/tasks/__init__.py
basebwa/components/apputil/tasks/init_db.py
basebwa/components/apputil/tasks/init_db.py~
basebwa/components/apputil/templates/blank_page.html
basebwa/components/apputil/templates/dynamic_control_panel.css
basebwa/components/apputil/templates/dynamic_control_panel.html
basebwa/components/apputil/templates/home_page.html
basebwa/components/apputil/templates/test_form.html
basebwa/config/__init__.py
basebwa/config/settings.py
basebwa/config/settings.py~
basebwa/config/site_settings.py.tpl
basebwa/lib/__init__.py
basebwa/lib/cpanel.py
basebwa/lib/cpanel.py~
basebwa/lib/forms.py
basebwa/lib/forms.py~
basebwa/lib/paster_tpl.py
basebwa/lib/paster_tpl.py~
basebwa/lib/paster_tpls/module/__init__.py
basebwa/lib/paster_tpls/module/actions.py
basebwa/lib/paster_tpls/module/commands.py
basebwa/lib/paster_tpls/module/forms.py
basebwa/lib/paster_tpls/module/settings.py_tmpl
basebwa/lib/paster_tpls/module/utils.py
basebwa/lib/paster_tpls/module/views.py
basebwa/lib/paster_tpls/module/views.py~
basebwa/lib/paster_tpls/module/model/__init__.py
basebwa/lib/paster_tpls/module/model/metadata.py
basebwa/lib/paster_tpls/module/model/orm.py
basebwa/lib/paster_tpls/module/templates/Index.html_tmpl
basebwa/lib/paster_tpls/project/MANIFEST.in_tmpl
basebwa/lib/paster_tpls/project/notes.txt
basebwa/lib/paster_tpls/project/setup.cfg
basebwa/lib/paster_tpls/project/setup.py_tmpl
basebwa/lib/paster_tpls/project/+package+/__init__.py
basebwa/lib/paster_tpls/project/+package+/applications.py
